qai_hub_models/__init__.py
qai_hub_models/_version.py
qai_hub_models/asset_bases.yaml
qai_hub_models/conftest.py
qai_hub_models/devices_and_chipsets.yaml
qai_hub_models/global_requirements.txt
qai_hub_models/requirements-dev.txt
qai_hub_models/requirements-gpu-dev.txt
qai_hub_models/requirements.txt
qai_hub_models/configs/__init__.py
qai_hub_models/configs/_info_yaml_enums.py
qai_hub_models/configs/_info_yaml_llm_details.py
qai_hub_models/configs/code_gen_yaml.py
qai_hub_models/configs/devices_and_chipsets_yaml.py
qai_hub_models/configs/info_yaml.py
qai_hub_models/configs/model_disable_reasons.py
qai_hub_models/configs/numerics_yaml.py
qai_hub_models/configs/perf_yaml.py
qai_hub_models/configs/tool_versions.py
qai_hub_models/datasets/__init__.py
qai_hub_models/datasets/ade20k.py
qai_hub_models/datasets/amazon_counterfactual.py
qai_hub_models/datasets/audioset.py
qai_hub_models/datasets/bsd300.py
qai_hub_models/datasets/camouflage_dataset.py
qai_hub_models/datasets/camvid.py
qai_hub_models/datasets/carvana.py
qai_hub_models/datasets/celebahq.py
qai_hub_models/datasets/cityscapes.py
qai_hub_models/datasets/cityscapes_lowres.py
qai_hub_models/datasets/coco.py
qai_hub_models/datasets/coco91class.py
qai_hub_models/datasets/coco_face.py
qai_hub_models/datasets/coco_foot_track_dataset.py
qai_hub_models/datasets/coco_panoptic_seg.py
qai_hub_models/datasets/coco_seg.py
qai_hub_models/datasets/cocobody.py
qai_hub_models/datasets/cocowholebody.py
qai_hub_models/datasets/cofw.py
qai_hub_models/datasets/common.py
qai_hub_models/datasets/configure_dataset.py
qai_hub_models/datasets/eg1800.py
qai_hub_models/datasets/face_attrib_dataset.py
qai_hub_models/datasets/face_det_lite.py
qai_hub_models/datasets/facemap_3dmm_dataset.py
qai_hub_models/datasets/foot_track_dataset.py
qai_hub_models/datasets/gear_guard_dataset.py
qai_hub_models/datasets/human_faces.py
qai_hub_models/datasets/human_poses.py
qai_hub_models/datasets/imagenet.py
qai_hub_models/datasets/imagenet_256.py
qai_hub_models-0.39.1.dist-info/licenses/LICENSE
qai_hub_models-0.39.1.dist-info/METADATA
qai_hub_models-0.39.1.dist-info/WHEEL
qai_hub_models-0.39.1.dist-info/top_level.txt
qai_hub_models-0.39.1.dist-info/RECORD
