Metadata-Version: 2.4
Name: qai_hub_models
Version: 0.39.1
Summary: Popular Machine Learning models optimized for Qualcomm chipsets.
Author-email: "Qualcomm® Technologies, Inc" <ai-hub-support@qti.qualcomm.com>
License-Expression: BSD-3-Clause
Project-URL: Homepage, https://aihub.qualcomm.com/models
Project-URL: GitHub, https://github.com/quic/ai-hub-models
Project-URL: Issues, https://github.com/quic/ai-hub-models/issues
Project-URL: Slack, https://aihub.qualcomm.com/community/slack
Project-URL: HuggingFace, https://huggingface.co/qualcomm
Classifier: Programming Language :: Python :: 3
Classifier: Programming Language :: Python :: 3.9
Classifier: Programming Language :: Python :: 3.10
Classifier: Programming Language :: Python :: 3.11
Classifier: Programming Language :: Python :: 3.12
Classifier: Operating System :: OS Independent
Requires-Python: <3.13,>=3.9
License-File: LICENSE
Requires-Dist: Pillow<12,>10
Requires-Dist: numpydoc==1.9.0
Requires-Dist: gdown==4.7.1
Requires-Dist: gitpython==3.1.42
Requires-Dist: huggingface_hub<1.0,>=0.34.0
Requires-Dist: ipython==8.12.3
Requires-Dist: numpy<2
Requires-Dist: onnx<1.20,>=1.17
Requires-Dist: onnxruntime<1.23,>=1.19
Requires-Dist: opencv-python<5,>4
Requires-Dist: pandas<2.3,>2
Requires-Dist: prettytable==3.11.0
Requires-Dist: requests_toolbelt==1.0.0
Requires-Dist: schema==0.7.5
Requires-Dist: torch<2.9.0,>=2.1
Requires-Dist: tabulate==0.9.0
Requires-Dist: torchaudio<2.9.0,>=2.1.2
Requires-Dist: torchvision<0.24.0,>=0.16
Requires-Dist: typing-extensions>=4.12.2
Requires-Dist: tqdm>=4.66
Requires-Dist: pyarrow==19.0.1
Requires-Dist: qai_hub>=0.34.0
Requires-Dist: datasets==2.17.0
Requires-Dist: ruamel-yaml==0.18.10
Requires-Dist: filelock>=3.16.1
Requires-Dist: pydantic<3,>=2
Requires-Dist: pydantic_yaml==1.4.0
Requires-Dist: scipy<2,>=1.8.1
Requires-Dist: pyquaternion==0.9.9
Requires-Dist: numba==0.60.0
Provides-Extra: dev
Requires-Dist: boto3<1.36,>=1.34; extra == "dev"
Requires-Dist: botocore<1.36,>=1.34; extra == "dev"
Requires-Dist: jinja2<3.2; extra == "dev"
Requires-Dist: mypy==1.13.0; extra == "dev"
Requires-Dist: pre-commit==4.0.1; extra == "dev"
Requires-Dist: pytest<9,>7; extra == "dev"
Requires-Dist: pytest-cov<5.2,>=5; extra == "dev"
Requires-Dist: pytest-xdist<4,>3; extra == "dev"
Requires-Dist: tflite==2.10.0; extra == "dev"
Requires-Dist: types-pillow==10.2.0.20240213; extra == "dev"
Requires-Dist: types-tabulate==0.9.0.20240106; extra == "dev"
Requires-Dist: types-requests==2.31.0.6; extra == "dev"
Requires-Dist: wheel==0.44.0; extra == "dev"
Requires-Dist: packaging<24,>23; extra == "dev"
Requires-Dist: adbutils>=2.8.0; extra == "dev"
Requires-Dist: boto3-stubs[s3]==1.36.9; extra == "dev"
Requires-Dist: setuptools>=75.8.0; extra == "dev"
Requires-Dist: build>=1.3.0; extra == "dev"
Provides-Extra: rtmdet
Requires-Dist: chumpy==0.71; extra == "rtmdet"
Requires-Dist: mmdet==3.3.0+mmcv220; extra == "rtmdet"
Requires-Dist: mmcv==2.2.0; extra == "rtmdet"
Requires-Dist: object-detection-metrics==0.4.post1; extra == "rtmdet"
Requires-Dist: fiftyone<1.9,>=1.0.1; extra == "rtmdet"
Requires-Dist: torchmetrics==1.4.0.post0; extra == "rtmdet"
Provides-Extra: lama-dilated
Requires-Dist: albumentations==0.5.2; extra == "lama-dilated"
Requires-Dist: pytorch-lightning<3,>2; extra == "lama-dilated"
Requires-Dist: webdataset==0.2.86; extra == "lama-dilated"
Requires-Dist: easydict==1.13; extra == "lama-dilated"
Requires-Dist: kornia==0.5.0; extra == "lama-dilated"
Requires-Dist: hydra-core==1.3.0; extra == "lama-dilated"
Requires-Dist: scikit-learn<1.6,>1.1; extra == "lama-dilated"
Requires-Dist: tensorboard==2.13.0; extra == "lama-dilated"
Provides-Extra: lama-dilated
Requires-Dist: albumentations==0.5.2; extra == "lama-dilated"
Requires-Dist: pytorch-lightning<3,>2; extra == "lama-dilated"
Requires-Dist: webdataset==0.2.86; extra == "lama-dilated"
Requires-Dist: easydict==1.13; extra == "lama-dilated"
Requires-Dist: kornia==0.5.0; extra == "lama-dilated"
Requires-Dist: hydra-core==1.3.0; extra == "lama-dilated"
Requires-Dist: scikit-learn<1.6,>1.1; extra == "lama-dilated"
Requires-Dist: tensorboard==2.13.0; extra == "lama-dilated"
Provides-Extra: rf-detr
Requires-Dist: object-detection-metrics==0.4.post1; extra == "rf-detr"
Requires-Dist: shapely==2.0.3; extra == "rf-detr"
Requires-Dist: fiftyone<1.9,>=1.0.1; extra == "rf-detr"
Requires-Dist: supervision==0.25.1; extra == "rf-detr"
Requires-Dist: peft~=0.17.1; extra == "rf-detr"
Provides-Extra: rf-detr
Requires-Dist: object-detection-metrics==0.4.post1; extra == "rf-detr"
Requires-Dist: shapely==2.0.3; extra == "rf-detr"
Requires-Dist: fiftyone<1.9,>=1.0.1; extra == "rf-detr"
Requires-Dist: supervision==0.25.1; extra == "rf-detr"
Requires-Dist: peft~=0.17.1; extra == "rf-detr"
Provides-Extra: dla102x
Requires-Dist: timm==1.0.15; extra == "dla102x"
Provides-Extra: fastsam-s
Requires-Dist: ultralytics~=8.3.0; extra == "fastsam-s"
Provides-Extra: fastsam-s
Requires-Dist: ultralytics~=8.3.0; extra == "fastsam-s"
Provides-Extra: whisper-small
Requires-Dist: jiwer==3.0.3; extra == "whisper-small"
Requires-Dist: transformers~=4.56.2; extra == "whisper-small"
Requires-Dist: audio2numpy==0.1.2; extra == "whisper-small"
Requires-Dist: scipy<2,>=1.8.1; extra == "whisper-small"
Requires-Dist: sounddevice==0.5.2; extra == "whisper-small"
Provides-Extra: whisper-small
Requires-Dist: jiwer==3.0.3; extra == "whisper-small"
Requires-Dist: transformers~=4.56.2; extra == "whisper-small"
Requires-Dist: audio2numpy==0.1.2; extra == "whisper-small"
Requires-Dist: scipy<2,>=1.8.1; extra == "whisper-small"
Requires-Dist: sounddevice==0.5.2; extra == "whisper-small"
Provides-Extra: rtmpose-body2d
Requires-Dist: chumpy==0.71; extra == "rtmpose-body2d"
Requires-Dist: mmdet==3.3.0+mmcv220; extra == "rtmpose-body2d"
Requires-Dist: mmpose==1.2.0; extra == "rtmpose-body2d"
Requires-Dist: mmcv==2.2.0; extra == "rtmpose-body2d"
Requires-Dist: matplotlib==3.7.3; extra == "rtmpose-body2d"
Provides-Extra: rtmpose-body2d
Requires-Dist: chumpy==0.71; extra == "rtmpose-body2d"
Requires-Dist: mmdet==3.3.0+mmcv220; extra == "rtmpose-body2d"
Requires-Dist: mmpose==1.2.0; extra == "rtmpose-body2d"
Requires-Dist: mmcv==2.2.0; extra == "rtmpose-body2d"
Requires-Dist: matplotlib==3.7.3; extra == "rtmpose-body2d"
Provides-Extra: stable-diffusion-v1-5
Requires-Dist: aimet-onnx==2.14.0; (sys_platform == "linux" and python_version == "3.10") and extra == "stable-diffusion-v1-5"
Requires-Dist: transformers~=4.56.2; extra == "stable-diffusion-v1-5"
Requires-Dist: diffusers[torch]~=0.35.1; extra == "stable-diffusion-v1-5"
Requires-Dist: onnx<1.20,>=1.17; extra == "stable-diffusion-v1-5"
Requires-Dist: onnxsim<=0.4.36; python_version < "3.12" and extra == "stable-diffusion-v1-5"
Requires-Dist: onnxsim-prebuilt==0.4.36.post1; python_version >= "3.12" and extra == "stable-diffusion-v1-5"
Provides-Extra: stable-diffusion-v1-5
Requires-Dist: aimet-onnx==2.14.0; (sys_platform == "linux" and python_version == "3.10") and extra == "stable-diffusion-v1-5"
Requires-Dist: transformers~=4.56.2; extra == "stable-diffusion-v1-5"
Requires-Dist: diffusers[torch]~=0.35.1; extra == "stable-diffusion-v1-5"
Requires-Dist: onnx<1.20,>=1.17; extra == "stable-diffusion-v1-5"
Requires-Dist: onnxsim<=0.4.36; python_version < "3.12" and extra == "stable-diffusion-v1-5"
Requires-Dist: onnxsim-prebuilt==0.4.36.post1; python_version >= "3.12" and extra == "stable-diffusion-v1-5"
Provides-Extra: detr-resnet101-dc5
Requires-Dist: transformers~=4.56.2; extra == "detr-resnet101-dc5"
Provides-Extra: detr-resnet101-dc5
Requires-Dist: transformers~=4.56.2; extra == "detr-resnet101-dc5"
Provides-Extra: fomm
Requires-Dist: imageio[ffmpeg]==2.31.5; extra == "fomm"
Requires-Dist: ffmpeg==1.4; extra == "fomm"
Requires-Dist: scikit-image<0.25,>0.21.0; extra == "fomm"
Requires-Dist: scikit-learn<1.6,>1.1; extra == "fomm"
Requires-Dist: matplotlib==3.7.5; extra == "fomm"
Requires-Dist: scipy<2,>=1.8.1; extra == "fomm"
Provides-Extra: conditional-detr-resnet50
Requires-Dist: transformers~=4.56.2; extra == "conditional-detr-resnet50"
Provides-Extra: conditional-detr-resnet50
Requires-Dist: transformers~=4.56.2; extra == "conditional-detr-resnet50"
Provides-Extra: sequencer2d
Requires-Dist: timm==1.0.15; extra == "sequencer2d"
Provides-Extra: whisper-large-v3-turbo
Requires-Dist: jiwer==3.0.3; extra == "whisper-large-v3-turbo"
Requires-Dist: transformers~=4.56.2; extra == "whisper-large-v3-turbo"
Requires-Dist: audio2numpy==0.1.2; extra == "whisper-large-v3-turbo"
Requires-Dist: scipy<2,>=1.8.1; extra == "whisper-large-v3-turbo"
Requires-Dist: sounddevice==0.5.2; extra == "whisper-large-v3-turbo"
Provides-Extra: whisper-large-v3-turbo
Requires-Dist: jiwer==3.0.3; extra == "whisper-large-v3-turbo"
Requires-Dist: transformers~=4.56.2; extra == "whisper-large-v3-turbo"
Requires-Dist: audio2numpy==0.1.2; extra == "whisper-large-v3-turbo"
Requires-Dist: scipy<2,>=1.8.1; extra == "whisper-large-v3-turbo"
Requires-Dist: sounddevice==0.5.2; extra == "whisper-large-v3-turbo"
Provides-Extra: mobilesam
Requires-Dist: pycocotools==2.0.7; extra == "mobilesam"
Requires-Dist: matplotlib==3.7.5; extra == "mobilesam"
Requires-Dist: timm==1.0.15; extra == "mobilesam"
Provides-Extra: face-det-lite
Requires-Dist: xtcocotools==1.14.3; extra == "face-det-lite"
Requires-Dist: object-detection-metrics==0.4.post1; extra == "face-det-lite"
Provides-Extra: face-det-lite
Requires-Dist: xtcocotools==1.14.3; extra == "face-det-lite"
Requires-Dist: object-detection-metrics==0.4.post1; extra == "face-det-lite"
Provides-Extra: yolov7
Requires-Dist: object-detection-metrics==0.4.post1; extra == "yolov7"
Requires-Dist: shapely==2.0.3; extra == "yolov7"
Requires-Dist: fiftyone<1.9,>=1.0.1; extra == "yolov7"
Provides-Extra: foot-track-net
Requires-Dist: object-detection-metrics==0.4.post1; extra == "foot-track-net"
Requires-Dist: shapely==2.0.3; extra == "foot-track-net"
Requires-Dist: fiftyone<1.9,>=1.0.1; extra == "foot-track-net"
Requires-Dist: xtcocotools==1.14.3; extra == "foot-track-net"
Provides-Extra: foot-track-net
Requires-Dist: object-detection-metrics==0.4.post1; extra == "foot-track-net"
Requires-Dist: shapely==2.0.3; extra == "foot-track-net"
Requires-Dist: fiftyone<1.9,>=1.0.1; extra == "foot-track-net"
Requires-Dist: xtcocotools==1.14.3; extra == "foot-track-net"
Provides-Extra: yolox
Requires-Dist: object-detection-metrics==0.4.post1; extra == "yolox"
Requires-Dist: loguru==0.7.3; extra == "yolox"
Requires-Dist: shapely==2.0.3; extra == "yolox"
Provides-Extra: yolov8-det
Requires-Dist: object-detection-metrics==0.4.post1; extra == "yolov8-det"
Requires-Dist: ultralytics~=8.3.0; extra == "yolov8-det"
Requires-Dist: shapely==2.0.3; extra == "yolov8-det"
Requires-Dist: fiftyone<1.9,>=1.0.1; extra == "yolov8-det"
Provides-Extra: yolov8-det
Requires-Dist: object-detection-metrics==0.4.post1; extra == "yolov8-det"
Requires-Dist: ultralytics~=8.3.0; extra == "yolov8-det"
Requires-Dist: shapely==2.0.3; extra == "yolov8-det"
Requires-Dist: fiftyone<1.9,>=1.0.1; extra == "yolov8-det"
Provides-Extra: llama-v3-1-8b-instruct
Requires-Dist: aimet-onnx==2.14.0; (sys_platform == "linux" and python_version == "3.10") and extra == "llama-v3-1-8b-instruct"
Requires-Dist: transformers==4.45.0; extra == "llama-v3-1-8b-instruct"
Requires-Dist: sentencepiece==0.2.0; extra == "llama-v3-1-8b-instruct"
Requires-Dist: psutil; extra == "llama-v3-1-8b-instruct"
Requires-Dist: onnx==1.17.0; extra == "llama-v3-1-8b-instruct"
Requires-Dist: torch==2.4.1; extra == "llama-v3-1-8b-instruct"
Requires-Dist: torchvision==0.19.1; extra == "llama-v3-1-8b-instruct"
Requires-Dist: onnxruntime==1.22; extra == "llama-v3-1-8b-instruct"
Provides-Extra: llama-v3-1-8b-instruct
Requires-Dist: aimet-onnx==2.14.0; (sys_platform == "linux" and python_version == "3.10") and extra == "llama-v3-1-8b-instruct"
Requires-Dist: transformers==4.45.0; extra == "llama-v3-1-8b-instruct"
Requires-Dist: sentencepiece==0.2.0; extra == "llama-v3-1-8b-instruct"
Requires-Dist: psutil; extra == "llama-v3-1-8b-instruct"
Requires-Dist: onnx==1.17.0; extra == "llama-v3-1-8b-instruct"
Requires-Dist: torch==2.4.1; extra == "llama-v3-1-8b-instruct"
Requires-Dist: torchvision==0.19.1; extra == "llama-v3-1-8b-instruct"
Requires-Dist: onnxruntime==1.22; extra == "llama-v3-1-8b-instruct"
Provides-Extra: hrnet-w48-ocr
Requires-Dist: yacs==0.1.8; extra == "hrnet-w48-ocr"
Provides-Extra: hrnet-w48-ocr
Requires-Dist: yacs==0.1.8; extra == "hrnet-w48-ocr"
Provides-Extra: falcon-v3-7b-instruct
Requires-Dist: aimet-onnx==2.14.0; (sys_platform == "linux" and python_version == "3.10") and extra == "falcon-v3-7b-instruct"
Requires-Dist: transformers==4.45.0; extra == "falcon-v3-7b-instruct"
Requires-Dist: sentencepiece==0.2.0; extra == "falcon-v3-7b-instruct"
Requires-Dist: psutil; extra == "falcon-v3-7b-instruct"
Requires-Dist: onnx==1.17.0; extra == "falcon-v3-7b-instruct"
Requires-Dist: torch==2.4.1; extra == "falcon-v3-7b-instruct"
Requires-Dist: torchvision==0.19.1; extra == "falcon-v3-7b-instruct"
Requires-Dist: onnxruntime==1.22; extra == "falcon-v3-7b-instruct"
Provides-Extra: falcon-v3-7b-instruct
Requires-Dist: aimet-onnx==2.14.0; (sys_platform == "linux" and python_version == "3.10") and extra == "falcon-v3-7b-instruct"
Requires-Dist: transformers==4.45.0; extra == "falcon-v3-7b-instruct"
Requires-Dist: sentencepiece==0.2.0; extra == "falcon-v3-7b-instruct"
Requires-Dist: psutil; extra == "falcon-v3-7b-instruct"
Requires-Dist: onnx==1.17.0; extra == "falcon-v3-7b-instruct"
Requires-Dist: torch==2.4.1; extra == "falcon-v3-7b-instruct"
Requires-Dist: torchvision==0.19.1; extra == "falcon-v3-7b-instruct"
Requires-Dist: onnxruntime==1.22; extra == "falcon-v3-7b-instruct"
Provides-Extra: llama-v3-taide-8b-chat
Requires-Dist: aimet-onnx==2.14.0; (sys_platform == "linux" and python_version == "3.10") and extra == "llama-v3-taide-8b-chat"
Requires-Dist: transformers==4.45.0; extra == "llama-v3-taide-8b-chat"
Requires-Dist: sentencepiece==0.2.0; extra == "llama-v3-taide-8b-chat"
Requires-Dist: psutil; extra == "llama-v3-taide-8b-chat"
Requires-Dist: onnx==1.17.0; extra == "llama-v3-taide-8b-chat"
Requires-Dist: torch==2.4.1; extra == "llama-v3-taide-8b-chat"
Requires-Dist: torchvision==0.19.1; extra == "llama-v3-taide-8b-chat"
Requires-Dist: onnxruntime==1.22; extra == "llama-v3-taide-8b-chat"
Provides-Extra: llama-v3-taide-8b-chat
Requires-Dist: aimet-onnx==2.14.0; (sys_platform == "linux" and python_version == "3.10") and extra == "llama-v3-taide-8b-chat"
Requires-Dist: transformers==4.45.0; extra == "llama-v3-taide-8b-chat"
Requires-Dist: sentencepiece==0.2.0; extra == "llama-v3-taide-8b-chat"
Requires-Dist: psutil; extra == "llama-v3-taide-8b-chat"
Requires-Dist: onnx==1.17.0; extra == "llama-v3-taide-8b-chat"
Requires-Dist: torch==2.4.1; extra == "llama-v3-taide-8b-chat"
Requires-Dist: torchvision==0.19.1; extra == "llama-v3-taide-8b-chat"
Requires-Dist: onnxruntime==1.22; extra == "llama-v3-taide-8b-chat"
Provides-Extra: efficientformer
Requires-Dist: timm==1.0.15; extra == "efficientformer"
Provides-Extra: video-mae
Requires-Dist: av==14.0.1; extra == "video-mae"
Requires-Dist: transformers~=4.56.2; extra == "video-mae"
Provides-Extra: video-mae
Requires-Dist: av==14.0.1; extra == "video-mae"
Requires-Dist: transformers~=4.56.2; extra == "video-mae"
Provides-Extra: whisper-small-quantized
Requires-Dist: aimet-onnx==2.14.0; (sys_platform == "linux" and python_version == "3.10") and extra == "whisper-small-quantized"
Requires-Dist: transformers~=4.56.2; extra == "whisper-small-quantized"
Requires-Dist: audio2numpy==0.1.2; extra == "whisper-small-quantized"
Requires-Dist: onnx<1.20,>=1.17; extra == "whisper-small-quantized"
Requires-Dist: onnxsim<=0.4.36; python_version < "3.12" and extra == "whisper-small-quantized"
Requires-Dist: onnxsim-prebuilt==0.4.36.post1; python_version >= "3.12" and extra == "whisper-small-quantized"
Requires-Dist: scipy<2,>=1.8.1; extra == "whisper-small-quantized"
Requires-Dist: sounddevice==0.5.2; extra == "whisper-small-quantized"
Provides-Extra: whisper-small-quantized
Requires-Dist: aimet-onnx==2.14.0; (sys_platform == "linux" and python_version == "3.10") and extra == "whisper-small-quantized"
Requires-Dist: transformers~=4.56.2; extra == "whisper-small-quantized"
Requires-Dist: audio2numpy==0.1.2; extra == "whisper-small-quantized"
Requires-Dist: onnx<1.20,>=1.17; extra == "whisper-small-quantized"
Requires-Dist: onnxsim<=0.4.36; python_version < "3.12" and extra == "whisper-small-quantized"
Requires-Dist: onnxsim-prebuilt==0.4.36.post1; python_version >= "3.12" and extra == "whisper-small-quantized"
Requires-Dist: scipy<2,>=1.8.1; extra == "whisper-small-quantized"
Requires-Dist: sounddevice==0.5.2; extra == "whisper-small-quantized"
Provides-Extra: litehrnet
Requires-Dist: chumpy==0.71; extra == "litehrnet"
Requires-Dist: mmdet==3.3.0+mmcv220; extra == "litehrnet"
Requires-Dist: mmpose==1.2.0; extra == "litehrnet"
Requires-Dist: mmcv==2.2.0; extra == "litehrnet"
Provides-Extra: deepbox
Requires-Dist: object-detection-metrics==0.4.post1; extra == "deepbox"
Requires-Dist: shapely==2.0.3; extra == "deepbox"
Requires-Dist: ultralytics~=8.3.0; extra == "deepbox"
Provides-Extra: detr-resnet50
Requires-Dist: transformers~=4.56.2; extra == "detr-resnet50"
Requires-Dist: object-detection-metrics==0.4.post1; extra == "detr-resnet50"
Requires-Dist: shapely==2.0.3; extra == "detr-resnet50"
Requires-Dist: fiftyone<1.9,>=1.0.1; extra == "detr-resnet50"
Provides-Extra: detr-resnet50
Requires-Dist: transformers~=4.56.2; extra == "detr-resnet50"
Requires-Dist: object-detection-metrics==0.4.post1; extra == "detr-resnet50"
Requires-Dist: shapely==2.0.3; extra == "detr-resnet50"
Requires-Dist: fiftyone<1.9,>=1.0.1; extra == "detr-resnet50"
Provides-Extra: hrnet-pose
Requires-Dist: yacs==0.1.8; extra == "hrnet-pose"
Requires-Dist: chumpy==0.71; extra == "hrnet-pose"
Requires-Dist: mmdet==3.3.0+mmcv220; extra == "hrnet-pose"
Requires-Dist: mmpose==1.2.0; extra == "hrnet-pose"
Requires-Dist: mmcv==2.2.0; extra == "hrnet-pose"
Requires-Dist: xtcocotools==1.14.3; extra == "hrnet-pose"
Provides-Extra: hrnet-pose
Requires-Dist: yacs==0.1.8; extra == "hrnet-pose"
Requires-Dist: chumpy==0.71; extra == "hrnet-pose"
Requires-Dist: mmdet==3.3.0+mmcv220; extra == "hrnet-pose"
Requires-Dist: mmpose==1.2.0; extra == "hrnet-pose"
Requires-Dist: mmcv==2.2.0; extra == "hrnet-pose"
Requires-Dist: xtcocotools==1.14.3; extra == "hrnet-pose"
Provides-Extra: depth-anything
Requires-Dist: matplotlib==3.7.5; extra == "depth-anything"
Requires-Dist: transformers~=4.56.2; extra == "depth-anything"
Provides-Extra: depth-anything
Requires-Dist: matplotlib==3.7.5; extra == "depth-anything"
Requires-Dist: transformers~=4.56.2; extra == "depth-anything"
Provides-Extra: nasnet
Requires-Dist: timm==1.0.15; extra == "nasnet"
Provides-Extra: yolov11-seg
Requires-Dist: ultralytics~=8.3.0; extra == "yolov11-seg"
Requires-Dist: shapely==2.0.3; extra == "yolov11-seg"
Requires-Dist: fiftyone<1.9,>=1.0.1; extra == "yolov11-seg"
Requires-Dist: torchmetrics==1.4.0.post0; extra == "yolov11-seg"
Provides-Extra: yolov11-seg
Requires-Dist: ultralytics~=8.3.0; extra == "yolov11-seg"
Requires-Dist: shapely==2.0.3; extra == "yolov11-seg"
Requires-Dist: fiftyone<1.9,>=1.0.1; extra == "yolov11-seg"
Requires-Dist: torchmetrics==1.4.0.post0; extra == "yolov11-seg"
Provides-Extra: ffnet-54s
Requires-Dist: scikit-image<0.25,>0.21.0; extra == "ffnet-54s"
Provides-Extra: ffnet-54s
Requires-Dist: scikit-image<0.25,>0.21.0; extra == "ffnet-54s"
Provides-Extra: whisper-base
Requires-Dist: jiwer==3.0.3; extra == "whisper-base"
Requires-Dist: transformers~=4.56.2; extra == "whisper-base"
Requires-Dist: audio2numpy==0.1.2; extra == "whisper-base"
Requires-Dist: scipy<2,>=1.8.1; extra == "whisper-base"
Requires-Dist: sounddevice==0.5.2; extra == "whisper-base"
Provides-Extra: whisper-base
Requires-Dist: jiwer==3.0.3; extra == "whisper-base"
Requires-Dist: transformers~=4.56.2; extra == "whisper-base"
Requires-Dist: audio2numpy==0.1.2; extra == "whisper-base"
Requires-Dist: scipy<2,>=1.8.1; extra == "whisper-base"
Requires-Dist: sounddevice==0.5.2; extra == "whisper-base"
Provides-Extra: llama-v3-1-sea-lion-3-5-8b-r
Requires-Dist: aimet-onnx==2.14.0; (sys_platform == "linux" and python_version == "3.10") and extra == "llama-v3-1-sea-lion-3-5-8b-r"
Requires-Dist: transformers==4.45.0; extra == "llama-v3-1-sea-lion-3-5-8b-r"
Requires-Dist: sentencepiece==0.2.0; extra == "llama-v3-1-sea-lion-3-5-8b-r"
Requires-Dist: psutil; extra == "llama-v3-1-sea-lion-3-5-8b-r"
Requires-Dist: onnx==1.17.0; extra == "llama-v3-1-sea-lion-3-5-8b-r"
Requires-Dist: torch==2.4.1; extra == "llama-v3-1-sea-lion-3-5-8b-r"
Requires-Dist: torchvision==0.19.1; extra == "llama-v3-1-sea-lion-3-5-8b-r"
Requires-Dist: onnxruntime==1.22; extra == "llama-v3-1-sea-lion-3-5-8b-r"
Provides-Extra: llama-v3-1-sea-lion-3-5-8b-r
Requires-Dist: aimet-onnx==2.14.0; (sys_platform == "linux" and python_version == "3.10") and extra == "llama-v3-1-sea-lion-3-5-8b-r"
Requires-Dist: transformers==4.45.0; extra == "llama-v3-1-sea-lion-3-5-8b-r"
Requires-Dist: sentencepiece==0.2.0; extra == "llama-v3-1-sea-lion-3-5-8b-r"
Requires-Dist: psutil; extra == "llama-v3-1-sea-lion-3-5-8b-r"
Requires-Dist: onnx==1.17.0; extra == "llama-v3-1-sea-lion-3-5-8b-r"
Requires-Dist: torch==2.4.1; extra == "llama-v3-1-sea-lion-3-5-8b-r"
Requires-Dist: torchvision==0.19.1; extra == "llama-v3-1-sea-lion-3-5-8b-r"
Requires-Dist: onnxruntime==1.22; extra == "llama-v3-1-sea-lion-3-5-8b-r"
Provides-Extra: llama-v3-8b-instruct
Requires-Dist: aimet-onnx==2.14.0; (sys_platform == "linux" and python_version == "3.10") and extra == "llama-v3-8b-instruct"
Requires-Dist: transformers==4.45.0; extra == "llama-v3-8b-instruct"
Requires-Dist: sentencepiece==0.2.0; extra == "llama-v3-8b-instruct"
Requires-Dist: psutil; extra == "llama-v3-8b-instruct"
Requires-Dist: onnx==1.17.0; extra == "llama-v3-8b-instruct"
Requires-Dist: torch==2.4.1; extra == "llama-v3-8b-instruct"
Requires-Dist: torchvision==0.19.1; extra == "llama-v3-8b-instruct"
Requires-Dist: onnxruntime==1.22; extra == "llama-v3-8b-instruct"
Provides-Extra: llama-v3-8b-instruct
Requires-Dist: aimet-onnx==2.14.0; (sys_platform == "linux" and python_version == "3.10") and extra == "llama-v3-8b-instruct"
Requires-Dist: transformers==4.45.0; extra == "llama-v3-8b-instruct"
Requires-Dist: sentencepiece==0.2.0; extra == "llama-v3-8b-instruct"
Requires-Dist: psutil; extra == "llama-v3-8b-instruct"
Requires-Dist: onnx==1.17.0; extra == "llama-v3-8b-instruct"
Requires-Dist: torch==2.4.1; extra == "llama-v3-8b-instruct"
Requires-Dist: torchvision==0.19.1; extra == "llama-v3-8b-instruct"
Requires-Dist: onnxruntime==1.22; extra == "llama-v3-8b-instruct"
Provides-Extra: resnet-mixed
Requires-Dist: av==14.0.1; extra == "resnet-mixed"
Provides-Extra: resnet-mixed
Requires-Dist: av==14.0.1; extra == "resnet-mixed"
Provides-Extra: track-anything
Requires-Dist: psutil<7,>6; extra == "track-anything"
Provides-Extra: track-anything
Requires-Dist: psutil<7,>6; extra == "track-anything"
Provides-Extra: yolov11-det
Requires-Dist: object-detection-metrics==0.4.post1; extra == "yolov11-det"
Requires-Dist: ultralytics~=8.3.0; extra == "yolov11-det"
Requires-Dist: shapely==2.0.3; extra == "yolov11-det"
Provides-Extra: yolov11-det
Requires-Dist: object-detection-metrics==0.4.post1; extra == "yolov11-det"
Requires-Dist: ultralytics~=8.3.0; extra == "yolov11-det"
Requires-Dist: shapely==2.0.3; extra == "yolov11-det"
Provides-Extra: detr-resnet50-dc5
Requires-Dist: transformers~=4.56.2; extra == "detr-resnet50-dc5"
Requires-Dist: timm==1.0.15; extra == "detr-resnet50-dc5"
Provides-Extra: detr-resnet50-dc5
Requires-Dist: transformers~=4.56.2; extra == "detr-resnet50-dc5"
Requires-Dist: timm==1.0.15; extra == "detr-resnet50-dc5"
Provides-Extra: fastsam-x
Requires-Dist: ultralytics~=8.3.0; extra == "fastsam-x"
Provides-Extra: fastsam-x
Requires-Dist: ultralytics~=8.3.0; extra == "fastsam-x"
Provides-Extra: bgnet
Requires-Dist: pysodmetrics==1.3.0; extra == "bgnet"
Provides-Extra: nomic-embed-text
Requires-Dist: transformers~=4.56.2; extra == "nomic-embed-text"
Requires-Dist: einops==0.3.2; extra == "nomic-embed-text"
Provides-Extra: nomic-embed-text
Requires-Dist: transformers~=4.56.2; extra == "nomic-embed-text"
Requires-Dist: einops==0.3.2; extra == "nomic-embed-text"
Provides-Extra: posenet-mobilenet
Requires-Dist: xtcocotools==1.14.3; extra == "posenet-mobilenet"
Provides-Extra: posenet-mobilenet
Requires-Dist: xtcocotools==1.14.3; extra == "posenet-mobilenet"
Provides-Extra: depth-anything-v2
Requires-Dist: matplotlib==3.7.5; extra == "depth-anything-v2"
Requires-Dist: transformers~=4.56.2; extra == "depth-anything-v2"
Provides-Extra: depth-anything-v2
Requires-Dist: matplotlib==3.7.5; extra == "depth-anything-v2"
Requires-Dist: transformers~=4.56.2; extra == "depth-anything-v2"
Provides-Extra: real-esrgan-general-x4v3
Requires-Dist: seaborn==0.11.0; extra == "real-esrgan-general-x4v3"
Requires-Dist: basicsr==1.4.2; extra == "real-esrgan-general-x4v3"
Provides-Extra: real-esrgan-general-x4v3
Requires-Dist: seaborn==0.11.0; extra == "real-esrgan-general-x4v3"
Requires-Dist: basicsr==1.4.2; extra == "real-esrgan-general-x4v3"
Provides-Extra: controlnet-canny
Requires-Dist: aimet-onnx==2.14.0; (sys_platform == "linux" and python_version == "3.10") and extra == "controlnet-canny"
Requires-Dist: transformers~=4.56.2; extra == "controlnet-canny"
Requires-Dist: diffusers[torch]~=0.35.1; extra == "controlnet-canny"
Requires-Dist: onnx<1.20,>=1.17; extra == "controlnet-canny"
Requires-Dist: onnxsim<=0.4.36; python_version < "3.12" and extra == "controlnet-canny"
Requires-Dist: onnxsim-prebuilt==0.4.36.post1; python_version >= "3.12" and extra == "controlnet-canny"
Provides-Extra: controlnet-canny
Requires-Dist: aimet-onnx==2.14.0; (sys_platform == "linux" and python_version == "3.10") and extra == "controlnet-canny"
Requires-Dist: transformers~=4.56.2; extra == "controlnet-canny"
Requires-Dist: diffusers[torch]~=0.35.1; extra == "controlnet-canny"
Requires-Dist: onnx<1.20,>=1.17; extra == "controlnet-canny"
Requires-Dist: onnxsim<=0.4.36; python_version < "3.12" and extra == "controlnet-canny"
Requires-Dist: onnxsim-prebuilt==0.4.36.post1; python_version >= "3.12" and extra == "controlnet-canny"
Provides-Extra: efficientvit-l2-cls
Requires-Dist: segment-anything==1.0; extra == "efficientvit-l2-cls"
Provides-Extra: efficientvit-l2-cls
Requires-Dist: segment-anything==1.0; extra == "efficientvit-l2-cls"
Provides-Extra: huggingface-wavlm-base-plus
Requires-Dist: transformers~=4.56.2; extra == "huggingface-wavlm-base-plus"
Requires-Dist: soundfile==0.13.1; extra == "huggingface-wavlm-base-plus"
Requires-Dist: librosa==0.10.1; extra == "huggingface-wavlm-base-plus"
Requires-Dist: jiwer==3.0.3; extra == "huggingface-wavlm-base-plus"
Requires-Dist: torch>=2.6; extra == "huggingface-wavlm-base-plus"
Provides-Extra: huggingface-wavlm-base-plus
Requires-Dist: transformers~=4.56.2; extra == "huggingface-wavlm-base-plus"
Requires-Dist: soundfile==0.13.1; extra == "huggingface-wavlm-base-plus"
Requires-Dist: librosa==0.10.1; extra == "huggingface-wavlm-base-plus"
Requires-Dist: jiwer==3.0.3; extra == "huggingface-wavlm-base-plus"
Requires-Dist: torch>=2.6; extra == "huggingface-wavlm-base-plus"
Provides-Extra: ffnet-78s-lowres
Requires-Dist: scikit-image<0.25,>0.21.0; extra == "ffnet-78s-lowres"
Provides-Extra: ffnet-78s-lowres
Requires-Dist: scikit-image<0.25,>0.21.0; extra == "ffnet-78s-lowres"
Provides-Extra: mask2former
Requires-Dist: transformers==4.51.3; extra == "mask2former"
Provides-Extra: easyocr
Requires-Dist: easyocr==1.7.2; extra == "easyocr"
Provides-Extra: resnet-3d
Requires-Dist: av==14.0.1; extra == "resnet-3d"
Provides-Extra: resnet-3d
Requires-Dist: av==14.0.1; extra == "resnet-3d"
Provides-Extra: ddcolor
Requires-Dist: timm==1.0.15; extra == "ddcolor"
Provides-Extra: yolov8-seg
Requires-Dist: ultralytics~=8.3.0; extra == "yolov8-seg"
Requires-Dist: shapely==2.0.3; extra == "yolov8-seg"
Requires-Dist: fiftyone<1.9,>=1.0.1; extra == "yolov8-seg"
Requires-Dist: torchmetrics==1.4.0.post0; extra == "yolov8-seg"
Provides-Extra: yolov8-seg
Requires-Dist: ultralytics~=8.3.0; extra == "yolov8-seg"
Requires-Dist: shapely==2.0.3; extra == "yolov8-seg"
Requires-Dist: fiftyone<1.9,>=1.0.1; extra == "yolov8-seg"
Requires-Dist: torchmetrics==1.4.0.post0; extra == "yolov8-seg"
Provides-Extra: detr-resnet101
Requires-Dist: transformers~=4.56.2; extra == "detr-resnet101"
Provides-Extra: detr-resnet101
Requires-Dist: transformers~=4.56.2; extra == "detr-resnet101"
Provides-Extra: midas
Requires-Dist: timm==1.0.15; extra == "midas"
Requires-Dist: matplotlib==3.7.5; extra == "midas"
Requires-Dist: scipy<2,>=1.8.1; extra == "midas"
Provides-Extra: yamnet
Requires-Dist: resampy==0.4.3; extra == "yamnet"
Requires-Dist: torchaudio<2.9.0,>=2.1.2; extra == "yamnet"
Requires-Dist: soundfile==0.13.1; extra == "yamnet"
Requires-Dist: torchmetrics==1.4.0.post0; extra == "yamnet"
Provides-Extra: ffnet-40s
Requires-Dist: scikit-image<0.25,>0.21.0; extra == "ffnet-40s"
Provides-Extra: ffnet-40s
Requires-Dist: scikit-image<0.25,>0.21.0; extra == "ffnet-40s"
Provides-Extra: openai-clip
Requires-Dist: ftfy==6.1.1; extra == "openai-clip"
Requires-Dist: regex==2023.10.3; extra == "openai-clip"
Provides-Extra: openai-clip
Requires-Dist: ftfy==6.1.1; extra == "openai-clip"
Requires-Dist: regex==2023.10.3; extra == "openai-clip"
Provides-Extra: levit
Requires-Dist: transformers~=4.56.2; extra == "levit"
Provides-Extra: llama-v3-2-1b-instruct
Requires-Dist: aimet-onnx==2.14.0; (sys_platform == "linux" and python_version == "3.10") and extra == "llama-v3-2-1b-instruct"
Requires-Dist: transformers==4.45.0; extra == "llama-v3-2-1b-instruct"
Requires-Dist: sentencepiece==0.2.0; extra == "llama-v3-2-1b-instruct"
Requires-Dist: psutil; extra == "llama-v3-2-1b-instruct"
Requires-Dist: onnx==1.17.0; extra == "llama-v3-2-1b-instruct"
Requires-Dist: torch==2.4.1; extra == "llama-v3-2-1b-instruct"
Requires-Dist: torchvision==0.19.1; extra == "llama-v3-2-1b-instruct"
Requires-Dist: onnxruntime==1.22; extra == "llama-v3-2-1b-instruct"
Provides-Extra: llama-v3-2-1b-instruct
Requires-Dist: aimet-onnx==2.14.0; (sys_platform == "linux" and python_version == "3.10") and extra == "llama-v3-2-1b-instruct"
Requires-Dist: transformers==4.45.0; extra == "llama-v3-2-1b-instruct"
Requires-Dist: sentencepiece==0.2.0; extra == "llama-v3-2-1b-instruct"
Requires-Dist: psutil; extra == "llama-v3-2-1b-instruct"
Requires-Dist: onnx==1.17.0; extra == "llama-v3-2-1b-instruct"
Requires-Dist: torch==2.4.1; extra == "llama-v3-2-1b-instruct"
Requires-Dist: torchvision==0.19.1; extra == "llama-v3-2-1b-instruct"
Requires-Dist: onnxruntime==1.22; extra == "llama-v3-2-1b-instruct"
Provides-Extra: yolov10-det
Requires-Dist: object-detection-metrics==0.4.post1; extra == "yolov10-det"
Requires-Dist: ultralytics~=8.3.0; extra == "yolov10-det"
Requires-Dist: shapely==2.0.3; extra == "yolov10-det"
Provides-Extra: yolov10-det
Requires-Dist: object-detection-metrics==0.4.post1; extra == "yolov10-det"
Requires-Dist: ultralytics~=8.3.0; extra == "yolov10-det"
Requires-Dist: shapely==2.0.3; extra == "yolov10-det"
Provides-Extra: ffnet-78s
Requires-Dist: scikit-image<0.25,>0.21.0; extra == "ffnet-78s"
Provides-Extra: ffnet-78s
Requires-Dist: scikit-image<0.25,>0.21.0; extra == "ffnet-78s"
Provides-Extra: resnet-2plus1d
Requires-Dist: av==14.0.1; extra == "resnet-2plus1d"
Provides-Extra: resnet-2plus1d
Requires-Dist: av==14.0.1; extra == "resnet-2plus1d"
Provides-Extra: llama-v2-7b-chat
Requires-Dist: transformers==4.41.1; extra == "llama-v2-7b-chat"
Requires-Dist: sentencepiece==0.2.0; extra == "llama-v2-7b-chat"
Requires-Dist: psutil; extra == "llama-v2-7b-chat"
Provides-Extra: llama-v2-7b-chat
Requires-Dist: transformers==4.41.1; extra == "llama-v2-7b-chat"
Requires-Dist: sentencepiece==0.2.0; extra == "llama-v2-7b-chat"
Requires-Dist: psutil; extra == "llama-v2-7b-chat"
Provides-Extra: yolov5
Requires-Dist: object-detection-metrics==0.4.post1; extra == "yolov5"
Requires-Dist: shapely==2.0.3; extra == "yolov5"
Requires-Dist: ultralytics~=8.3.0; extra == "yolov5"
Provides-Extra: ffnet-122ns-lowres
Requires-Dist: scikit-image<0.25,>0.21.0; extra == "ffnet-122ns-lowres"
Provides-Extra: ffnet-122ns-lowres
Requires-Dist: scikit-image<0.25,>0.21.0; extra == "ffnet-122ns-lowres"
Provides-Extra: efficientvit-b2-cls
Requires-Dist: segment-anything==1.0; extra == "efficientvit-b2-cls"
Provides-Extra: efficientvit-b2-cls
Requires-Dist: segment-anything==1.0; extra == "efficientvit-b2-cls"
Provides-Extra: yolov6
Requires-Dist: object-detection-metrics==0.4.post1; extra == "yolov6"
Requires-Dist: shapely==2.0.3; extra == "yolov6"
Provides-Extra: efficientvit-l2-seg
Requires-Dist: segment-anything==1.0; extra == "efficientvit-l2-seg"
Provides-Extra: efficientvit-l2-seg
Requires-Dist: segment-anything==1.0; extra == "efficientvit-l2-seg"
Provides-Extra: llama-v3-2-3b-instruct
Requires-Dist: aimet-onnx==2.14.0; (sys_platform == "linux" and python_version == "3.10") and extra == "llama-v3-2-3b-instruct"
Requires-Dist: transformers==4.45.0; extra == "llama-v3-2-3b-instruct"
Requires-Dist: sentencepiece==0.2.0; extra == "llama-v3-2-3b-instruct"
Requires-Dist: psutil; extra == "llama-v3-2-3b-instruct"
Requires-Dist: onnx==1.17.0; extra == "llama-v3-2-3b-instruct"
Requires-Dist: torch==2.4.1; extra == "llama-v3-2-3b-instruct"
Requires-Dist: torchvision==0.19.1; extra == "llama-v3-2-3b-instruct"
Requires-Dist: onnxruntime==1.22; extra == "llama-v3-2-3b-instruct"
Provides-Extra: llama-v3-2-3b-instruct
Requires-Dist: aimet-onnx==2.14.0; (sys_platform == "linux" and python_version == "3.10") and extra == "llama-v3-2-3b-instruct"
Requires-Dist: transformers==4.45.0; extra == "llama-v3-2-3b-instruct"
Requires-Dist: sentencepiece==0.2.0; extra == "llama-v3-2-3b-instruct"
Requires-Dist: psutil; extra == "llama-v3-2-3b-instruct"
Requires-Dist: onnx==1.17.0; extra == "llama-v3-2-3b-instruct"
Requires-Dist: torch==2.4.1; extra == "llama-v3-2-3b-instruct"
Requires-Dist: torchvision==0.19.1; extra == "llama-v3-2-3b-instruct"
Requires-Dist: onnxruntime==1.22; extra == "llama-v3-2-3b-instruct"
Provides-Extra: yolov3
Requires-Dist: ultralytics~=8.3.0; extra == "yolov3"
Requires-Dist: object-detection-metrics==0.4.post1; extra == "yolov3"
Requires-Dist: shapely==2.0.3; extra == "yolov3"
Provides-Extra: facemap-3dmm
Requires-Dist: scikit-image<0.25,>0.21.0; extra == "facemap-3dmm"
Requires-Dist: xtcocotools==1.14.3; extra == "facemap-3dmm"
Provides-Extra: facemap-3dmm
Requires-Dist: scikit-image<0.25,>0.21.0; extra == "facemap-3dmm"
Requires-Dist: xtcocotools==1.14.3; extra == "facemap-3dmm"
Provides-Extra: trocr
Requires-Dist: transformers~=4.56.2; extra == "trocr"
Requires-Dist: sentencepiece==0.2.0; extra == "trocr"
Requires-Dist: torch>=2.6; extra == "trocr"
Provides-Extra: mediapipe-selfie
Requires-Dist: tflite==2.10.0; extra == "mediapipe-selfie"
Provides-Extra: mediapipe-selfie
Requires-Dist: tflite==2.10.0; extra == "mediapipe-selfie"
Provides-Extra: stable-diffusion-v2-1
Requires-Dist: aimet-onnx==2.14.0; (sys_platform == "linux" and python_version == "3.10") and extra == "stable-diffusion-v2-1"
Requires-Dist: transformers~=4.56.2; extra == "stable-diffusion-v2-1"
Requires-Dist: diffusers[torch]~=0.35.1; extra == "stable-diffusion-v2-1"
Requires-Dist: onnx<1.20,>=1.17; extra == "stable-diffusion-v2-1"
Requires-Dist: onnxsim<=0.4.36; python_version < "3.12" and extra == "stable-diffusion-v2-1"
Requires-Dist: onnxsim-prebuilt==0.4.36.post1; python_version >= "3.12" and extra == "stable-diffusion-v2-1"
Provides-Extra: stable-diffusion-v2-1
Requires-Dist: aimet-onnx==2.14.0; (sys_platform == "linux" and python_version == "3.10") and extra == "stable-diffusion-v2-1"
Requires-Dist: transformers~=4.56.2; extra == "stable-diffusion-v2-1"
Requires-Dist: diffusers[torch]~=0.35.1; extra == "stable-diffusion-v2-1"
Requires-Dist: onnx<1.20,>=1.17; extra == "stable-diffusion-v2-1"
Requires-Dist: onnxsim<=0.4.36; python_version < "3.12" and extra == "stable-diffusion-v2-1"
Requires-Dist: onnxsim-prebuilt==0.4.36.post1; python_version >= "3.12" and extra == "stable-diffusion-v2-1"
Provides-Extra: real-esrgan-x4plus
Requires-Dist: seaborn==0.11.0; extra == "real-esrgan-x4plus"
Requires-Dist: basicsr==1.4.2; extra == "real-esrgan-x4plus"
Provides-Extra: real-esrgan-x4plus
Requires-Dist: seaborn==0.11.0; extra == "real-esrgan-x4plus"
Requires-Dist: basicsr==1.4.2; extra == "real-esrgan-x4plus"
Provides-Extra: qwen2-5-7b-instruct
Requires-Dist: onnx==1.17.0; extra == "qwen2-5-7b-instruct"
Requires-Dist: transformers==4.45.0; extra == "qwen2-5-7b-instruct"
Requires-Dist: psutil; extra == "qwen2-5-7b-instruct"
Provides-Extra: qwen2-5-7b-instruct
Requires-Dist: onnx==1.17.0; extra == "qwen2-5-7b-instruct"
Requires-Dist: transformers==4.45.0; extra == "qwen2-5-7b-instruct"
Requires-Dist: psutil; extra == "qwen2-5-7b-instruct"
Provides-Extra: sam2
Requires-Dist: pycocotools==2.0.7; extra == "sam2"
Requires-Dist: matplotlib==3.7.5; extra == "sam2"
Requires-Dist: hydra-core==1.3.0; extra == "sam2"
Requires-Dist: iopath==0.1.10; extra == "sam2"
Provides-Extra: whisper-tiny
Requires-Dist: jiwer==3.0.3; extra == "whisper-tiny"
Requires-Dist: transformers~=4.56.2; extra == "whisper-tiny"
Requires-Dist: audio2numpy==0.1.2; extra == "whisper-tiny"
Requires-Dist: scipy<2,>=1.8.1; extra == "whisper-tiny"
Requires-Dist: sounddevice==0.5.2; extra == "whisper-tiny"
Provides-Extra: whisper-tiny
Requires-Dist: jiwer==3.0.3; extra == "whisper-tiny"
Requires-Dist: transformers~=4.56.2; extra == "whisper-tiny"
Requires-Dist: audio2numpy==0.1.2; extra == "whisper-tiny"
Requires-Dist: scipy<2,>=1.8.1; extra == "whisper-tiny"
Requires-Dist: sounddevice==0.5.2; extra == "whisper-tiny"
Provides-Extra: mobile-vit
Requires-Dist: transformers~=4.56.2; extra == "mobile-vit"
Requires-Dist: torch>=2.6; extra == "mobile-vit"
Provides-Extra: mobile-vit
Requires-Dist: transformers~=4.56.2; extra == "mobile-vit"
Requires-Dist: torch>=2.6; extra == "mobile-vit"
Provides-Extra: beit
Requires-Dist: transformers~=4.56.2; extra == "beit"
Dynamic: license-file
Dynamic: provides-extra
Dynamic: requires-dist
